{"nodes": [{"id": "c_users_bobby_onedrive_desktop_new_new_src_main_java_com_example_demo_dto_productresponse_java", "label": "ProductResponse.java", "file_type": "code", "source_file": "C:\\Users\\bobby\\OneDrive\\Desktop\\new\\new\\src\\main\\java\\com\\example\\demo\\dto\\ProductResponse.java", "source_location": "L1"}, {"id": "productresponse_productresponse", "label": "ProductResponse", "file_type": "code", "source_file": "C:\\Users\\bobby\\OneDrive\\Desktop\\new\\new\\src\\main\\java\\com\\example\\demo\\dto\\ProductResponse.java", "source_location": "L9"}, {"id": "productresponse_productresponse_productresponse", "label": ".ProductResponse()", "file_type": "code", "source_file": "C:\\Users\\bobby\\OneDrive\\Desktop\\new\\new\\src\\main\\java\\com\\example\\demo\\dto\\ProductResponse.java", "source_location": "L43"}, {"id": "productresponse_productresponse_from", "label": ".from()", "file_type": "code", "source_file": "C:\\Users\\bobby\\OneDrive\\Desktop\\new\\new\\src\\main\\java\\com\\example\\demo\\dto\\ProductResponse.java", "source_location": "L77"}, {"id": "productresponse_productresponse_getid", "label": ".getId()", "file_type": "code", "source_file": "C:\\Users\\bobby\\OneDrive\\Desktop\\new\\new\\src\\main\\java\\com\\example\\demo\\dto\\ProductResponse.java", "source_location": "L121"}, {"id": "productresponse_productresponse_getname", "label": ".getName()", "file_type": "code", "source_file": "C:\\Users\\bobby\\OneDrive\\Desktop\\new\\new\\src\\main\\java\\com\\example\\demo\\dto\\ProductResponse.java", "source_location": "L125"}, {"id": "productresponse_productresponse_getproductid", "label": ".getProductId()", "file_type": "code", "source_file": "C:\\Users\\bobby\\OneDrive\\Desktop\\new\\new\\src\\main\\java\\com\\example\\demo\\dto\\ProductResponse.java", "source_location": "L129"}, {"id": "productresponse_productresponse_getsku", "label": ".getSku()", "file_type": "code", "source_file": "C:\\Users\\bobby\\OneDrive\\Desktop\\new\\new\\src\\main\\java\\com\\example\\demo\\dto\\ProductResponse.java", "source_location": "L133"}, {"id": "productresponse_productresponse_getclientid", "label": ".getClientId()", "file_type": "code", "source_file": "C:\\Users\\bobby\\OneDrive\\Desktop\\new\\new\\src\\main\\java\\com\\example\\demo\\dto\\ProductResponse.java", "source_location": "L137"}, {"id": "productresponse_productresponse_getclientname", "label": ".getClientName()", "file_type": "code", "source_file": "C:\\Users\\bobby\\OneDrive\\Desktop\\new\\new\\src\\main\\java\\com\\example\\demo\\dto\\ProductResponse.java", "source_location": "L141"}, {"id": "productresponse_productresponse_getclientemail", "label": ".getClientEmail()", "file_type": "code", "source_file": "C:\\Users\\bobby\\OneDrive\\Desktop\\new\\new\\src\\main\\java\\com\\example\\demo\\dto\\ProductResponse.java", "source_location": "L145"}, {"id": "productresponse_productresponse_getclientorganisationname", "label": ".getClientOrganisationName()", "file_type": "code", "source_file": "C:\\Users\\bobby\\OneDrive\\Desktop\\new\\new\\src\\main\\java\\com\\example\\demo\\dto\\ProductResponse.java", "source_location": "L149"}, {"id": "productresponse_productresponse_getclientorganisationaddress", "label": ".getClientOrganisationAddress()", "file_type": "code", "source_file": "C:\\Users\\bobby\\OneDrive\\Desktop\\new\\new\\src\\main\\java\\com\\example\\demo\\dto\\ProductResponse.java", "source_location": "L153"}, {"id": "productresponse_productresponse_getclientphone", "label": ".getClientPhone()", "file_type": "code", "source_file": "C:\\Users\\bobby\\OneDrive\\Desktop\\new\\new\\src\\main\\java\\com\\example\\demo\\dto\\ProductResponse.java", "source_location": "L157"}, {"id": "productresponse_productresponse_getfcid", "label": ".getFcId()", "file_type": "code", "source_file": "C:\\Users\\bobby\\OneDrive\\Desktop\\new\\new\\src\\main\\java\\com\\example\\demo\\dto\\ProductResponse.java", "source_location": "L161"}, {"id": "productresponse_productresponse_getfclocation", "label": ".getFcLocation()", "file_type": "code", "source_file": "C:\\Users\\bobby\\OneDrive\\Desktop\\new\\new\\src\\main\\java\\com\\example\\demo\\dto\\ProductResponse.java", "source_location": "L165"}, {"id": "productresponse_productresponse_getdescription", "label": ".getDescription()", "file_type": "code", "source_file": "C:\\Users\\bobby\\OneDrive\\Desktop\\new\\new\\src\\main\\java\\com\\example\\demo\\dto\\ProductResponse.java", "source_location": "L169"}, {"id": "productresponse_productresponse_getprice", "label": ".getPrice()", "file_type": "code", "source_file": "C:\\Users\\bobby\\OneDrive\\Desktop\\new\\new\\src\\main\\java\\com\\example\\demo\\dto\\ProductResponse.java", "source_location": "L173"}, {"id": "productresponse_productresponse_getquantity", "label": ".getQuantity()", "file_type": "code", "source_file": "C:\\Users\\bobby\\OneDrive\\Desktop\\new\\new\\src\\main\\java\\com\\example\\demo\\dto\\ProductResponse.java", "source_location": "L177"}], "edges": [{"source": "c_users_bobby_onedrive_desktop_new_new_src_main_java_com_example_demo_dto_productresponse_java", "target": "product", "relation": "imports", "confidence": "EXTRACTED", "source_file": "C:\\Users\\bobby\\OneDrive\\Desktop\\new\\new\\src\\main\\java\\com\\example\\demo\\dto\\ProductResponse.java", "source_location": "L3", "weight": 1.0}, {"source": "c_users_bobby_onedrive_desktop_new_new_src_main_java_com_example_demo_dto_productresponse_java", "target": "client", "relation": "imports", "confidence": "EXTRACTED", "source_file": "C:\\Users\\bobby\\OneDrive\\Desktop\\new\\new\\src\\main\\java\\com\\example\\demo\\dto\\ProductResponse.java", "source_location": "L4", "weight": 1.0}, {"source": "c_users_bobby_onedrive_desktop_new_new_src_main_java_com_example_demo_dto_productresponse_java", "target": "schema", "relation": "imports", "confidence": "EXTRACTED", "source_file": "C:\\Users\\bobby\\OneDrive\\Desktop\\new\\new\\src\\main\\java\\com\\example\\demo\\dto\\ProductResponse.java", "source_location": "L5", "weight": 1.0}, {"source": "c_users_bobby_onedrive_desktop_new_new_src_main_java_com_example_demo_dto_productresponse_java", "target": "entitynotfoundexception", "relation": "imports", "confidence": "EXTRACTED", "source_file": "C:\\Users\\bobby\\OneDrive\\Desktop\\new\\new\\src\\main\\java\\com\\example\\demo\\dto\\ProductResponse.java", "source_location": "L6", "weight": 1.0}, {"source": "c_users_bobby_onedrive_desktop_new_new_src_main_java_com_example_demo_dto_productresponse_java", "target": "bigdecimal", "relation": "imports", "confidence": "EXTRACTED", "source_file": "C:\\Users\\bobby\\OneDrive\\Desktop\\new\\new\\src\\main\\java\\com\\example\\demo\\dto\\ProductResponse.java", "source_location": "L7", "weight": 1.0}, {"source": "c_users_bobby_onedrive_desktop_new_new_src_main_java_com_example_demo_dto_productresponse_java", "target": "productresponse_productresponse", "relation": "contains", "confidence": "EXTRACTED", "source_file": "C:\\Users\\bobby\\OneDrive\\Desktop\\new\\new\\src\\main\\java\\com\\example\\demo\\dto\\ProductResponse.java", "source_location": "L9", "weight": 1.0}, {"source": "productresponse_productresponse", "target": "productresponse_productresponse_productresponse", "relation": "method", "confidence": "EXTRACTED", "source_file": "C:\\Users\\bobby\\OneDrive\\Desktop\\new\\new\\src\\main\\java\\com\\example\\demo\\dto\\ProductResponse.java", "source_location": "L43", "weight": 1.0}, {"source": "productresponse_productresponse", "target": "productresponse_productresponse_from", "relation": "method", "confidence": "EXTRACTED", "source_file": "C:\\Users\\bobby\\OneDrive\\Desktop\\new\\new\\src\\main\\java\\com\\example\\demo\\dto\\ProductResponse.java", "source_location": "L77", "weight": 1.0}, {"source": "productresponse_productresponse", "target": "productresponse_productresponse_getid", "relation": "method", "confidence": "EXTRACTED", "source_file": "C:\\Users\\bobby\\OneDrive\\Desktop\\new\\new\\src\\main\\java\\com\\example\\demo\\dto\\ProductResponse.java", "source_location": "L121", "weight": 1.0}, {"source": "productresponse_productresponse", "target": "productresponse_productresponse_getname", "relation": "method", "confidence": "EXTRACTED", "source_file": "C:\\Users\\bobby\\OneDrive\\Desktop\\new\\new\\src\\main\\java\\com\\example\\demo\\dto\\ProductResponse.java", "source_location": "L125", "weight": 1.0}, {"source": "productresponse_productresponse", "target": "productresponse_productresponse_getproductid", "relation": "method", "confidence": "EXTRACTED", "source_file": "C:\\Users\\bobby\\OneDrive\\Desktop\\new\\new\\src\\main\\java\\com\\example\\demo\\dto\\ProductResponse.java", "source_location": "L129", "weight": 1.0}, {"source": "productresponse_productresponse", "target": "productresponse_productresponse_getsku", "relation": "method", "confidence": "EXTRACTED", "source_file": "C:\\Users\\bobby\\OneDrive\\Desktop\\new\\new\\src\\main\\java\\com\\example\\demo\\dto\\ProductResponse.java", "source_location": "L133", "weight": 1.0}, {"source": "productresponse_productresponse", "target": "productresponse_productresponse_getclientid", "relation": "method", "confidence": "EXTRACTED", "source_file": "C:\\Users\\bobby\\OneDrive\\Desktop\\new\\new\\src\\main\\java\\com\\example\\demo\\dto\\ProductResponse.java", "source_location": "L137", "weight": 1.0}, {"source": "productresponse_productresponse", "target": "productresponse_productresponse_getclientname", "relation": "method", "confidence": "EXTRACTED", "source_file": "C:\\Users\\bobby\\OneDrive\\Desktop\\new\\new\\src\\main\\java\\com\\example\\demo\\dto\\ProductResponse.java", "source_location": "L141", "weight": 1.0}, {"source": "productresponse_productresponse", "target": "productresponse_productresponse_getclientemail", "relation": "method", "confidence": "EXTRACTED", "source_file": "C:\\Users\\bobby\\OneDrive\\Desktop\\new\\new\\src\\main\\java\\com\\example\\demo\\dto\\ProductResponse.java", "source_location": "L145", "weight": 1.0}, {"source": "productresponse_productresponse", "target": "productresponse_productresponse_getclientorganisationname", "relation": "method", "confidence": "EXTRACTED", "source_file": "C:\\Users\\bobby\\OneDrive\\Desktop\\new\\new\\src\\main\\java\\com\\example\\demo\\dto\\ProductResponse.java", "source_location": "L149", "weight": 1.0}, {"source": "productresponse_productresponse", "target": "productresponse_productresponse_getclientorganisationaddress", "relation": "method", "confidence": "EXTRACTED", "source_file": "C:\\Users\\bobby\\OneDrive\\Desktop\\new\\new\\src\\main\\java\\com\\example\\demo\\dto\\ProductResponse.java", "source_location": "L153", "weight": 1.0}, {"source": "productresponse_productresponse", "target": "productresponse_productresponse_getclientphone", "relation": "method", "confidence": "EXTRACTED", "source_file": "C:\\Users\\bobby\\OneDrive\\Desktop\\new\\new\\src\\main\\java\\com\\example\\demo\\dto\\ProductResponse.java", "source_location": "L157", "weight": 1.0}, {"source": "productresponse_productresponse", "target": "productresponse_productresponse_getfcid", "relation": "method", "confidence": "EXTRACTED", "source_file": "C:\\Users\\bobby\\OneDrive\\Desktop\\new\\new\\src\\main\\java\\com\\example\\demo\\dto\\ProductResponse.java", "source_location": "L161", "weight": 1.0}, {"source": "productresponse_productresponse", "target": "productresponse_productresponse_getfclocation", "relation": "method", "confidence": "EXTRACTED", "source_file": "C:\\Users\\bobby\\OneDrive\\Desktop\\new\\new\\src\\main\\java\\com\\example\\demo\\dto\\ProductResponse.java", "source_location": "L165", "weight": 1.0}, {"source": "productresponse_productresponse", "target": "productresponse_productresponse_getdescription", "relation": "method", "confidence": "EXTRACTED", "source_file": "C:\\Users\\bobby\\OneDrive\\Desktop\\new\\new\\src\\main\\java\\com\\example\\demo\\dto\\ProductResponse.java", "source_location": "L169", "weight": 1.0}, {"source": "productresponse_productresponse", "target": "productresponse_productresponse_getprice", "relation": "method", "confidence": "EXTRACTED", "source_file": "C:\\Users\\bobby\\OneDrive\\Desktop\\new\\new\\src\\main\\java\\com\\example\\demo\\dto\\ProductResponse.java", "source_location": "L173", "weight": 1.0}, {"source": "productresponse_productresponse", "target": "productresponse_productresponse_getquantity", "relation": "method", "confidence": "EXTRACTED", "source_file": "C:\\Users\\bobby\\OneDrive\\Desktop\\new\\new\\src\\main\\java\\com\\example\\demo\\dto\\ProductResponse.java", "source_location": "L177", "weight": 1.0}, {"source": "productresponse_productresponse_from", "target": "productresponse_productresponse_getfcid", "relation": "calls", "confidence": "EXTRACTED", "source_file": "C:\\Users\\bobby\\OneDrive\\Desktop\\new\\new\\src\\main\\java\\com\\example\\demo\\dto\\ProductResponse.java", "source_location": "L85", "weight": 1.0}, {"source": "productresponse_productresponse_from", "target": "productresponse_productresponse_getid", "relation": "calls", "confidence": "EXTRACTED", "source_file": "C:\\Users\\bobby\\OneDrive\\Desktop\\new\\new\\src\\main\\java\\com\\example\\demo\\dto\\ProductResponse.java", "source_location": "L91", "weight": 1.0}, {"source": "productresponse_productresponse_from", "target": "productresponse_productresponse_getname", "relation": "calls", "confidence": "EXTRACTED", "source_file": "C:\\Users\\bobby\\OneDrive\\Desktop\\new\\new\\src\\main\\java\\com\\example\\demo\\dto\\ProductResponse.java", "source_location": "L92", "weight": 1.0}, {"source": "productresponse_productresponse_from", "target": "productresponse_productresponse_getproductid", "relation": "calls", "confidence": "EXTRACTED", "source_file": "C:\\Users\\bobby\\OneDrive\\Desktop\\new\\new\\src\\main\\java\\com\\example\\demo\\dto\\ProductResponse.java", "source_location": "L105", "weight": 1.0}, {"source": "productresponse_productresponse_from", "target": "productresponse_productresponse_getsku", "relation": "calls", "confidence": "EXTRACTED", "source_file": "C:\\Users\\bobby\\OneDrive\\Desktop\\new\\new\\src\\main\\java\\com\\example\\demo\\dto\\ProductResponse.java", "source_location": "L106", "weight": 1.0}, {"source": "productresponse_productresponse_from", "target": "productresponse_productresponse_getdescription", "relation": "calls", "confidence": "EXTRACTED", "source_file": "C:\\Users\\bobby\\OneDrive\\Desktop\\new\\new\\src\\main\\java\\com\\example\\demo\\dto\\ProductResponse.java", "source_location": "L115", "weight": 1.0}, {"source": "productresponse_productresponse_from", "target": "productresponse_productresponse_getprice", "relation": "calls", "confidence": "EXTRACTED", "source_file": "C:\\Users\\bobby\\OneDrive\\Desktop\\new\\new\\src\\main\\java\\com\\example\\demo\\dto\\ProductResponse.java", "source_location": "L116", "weight": 1.0}, {"source": "productresponse_productresponse_from", "target": "productresponse_productresponse_getquantity", "relation": "calls", "confidence": "EXTRACTED", "source_file": "C:\\Users\\bobby\\OneDrive\\Desktop\\new\\new\\src\\main\\java\\com\\example\\demo\\dto\\ProductResponse.java", "source_location": "L117", "weight": 1.0}], "raw_calls": [{"caller_nid": "productresponse_productresponse_from", "callee": "getFcInfo", "source_file": "C:\\Users\\bobby\\OneDrive\\Desktop\\new\\new\\src\\main\\java\\com\\example\\demo\\dto\\ProductResponse.java", "source_location": "L85"}, {"caller_nid": "productresponse_productresponse_from", "callee": "getLocation", "source_file": "C:\\Users\\bobby\\OneDrive\\Desktop\\new\\new\\src\\main\\java\\com\\example\\demo\\dto\\ProductResponse.java", "source_location": "L86"}, {"caller_nid": "productresponse_productresponse_from", "callee": "getFcInfo", "source_file": "C:\\Users\\bobby\\OneDrive\\Desktop\\new\\new\\src\\main\\java\\com\\example\\demo\\dto\\ProductResponse.java", "source_location": "L86"}, {"caller_nid": "productresponse_productresponse_from", "callee": "getClient", "source_file": "C:\\Users\\bobby\\OneDrive\\Desktop\\new\\new\\src\\main\\java\\com\\example\\demo\\dto\\ProductResponse.java", "source_location": "L89"}, {"caller_nid": "productresponse_productresponse_from", "callee": "getEmail", "source_file": "C:\\Users\\bobby\\OneDrive\\Desktop\\new\\new\\src\\main\\java\\com\\example\\demo\\dto\\ProductResponse.java", "source_location": "L93"}, {"caller_nid": "productresponse_productresponse_from", "callee": "getOrganisationName", "source_file": "C:\\Users\\bobby\\OneDrive\\Desktop\\new\\new\\src\\main\\java\\com\\example\\demo\\dto\\ProductResponse.java", "source_location": "L94"}, {"caller_nid": "productresponse_productresponse_from", "callee": "getOrganisationAddress", "source_file": "C:\\Users\\bobby\\OneDrive\\Desktop\\new\\new\\src\\main\\java\\com\\example\\demo\\dto\\ProductResponse.java", "source_location": "L95"}, {"caller_nid": "productresponse_productresponse_from", "callee": "getPhone", "source_file": "C:\\Users\\bobby\\OneDrive\\Desktop\\new\\new\\src\\main\\java\\com\\example\\demo\\dto\\ProductResponse.java", "source_location": "L96"}]}