{"nodes": [{"id": "c_users_bobby_onedrive_desktop_new_new_src_main_java_com_example_demo_dto_orderitemresponse_java", "label": "OrderItemResponse.java", "file_type": "code", "source_file": "C:\\Users\\bobby\\OneDrive\\Desktop\\new\\new\\src\\main\\java\\com\\example\\demo\\dto\\OrderItemResponse.java", "source_location": "L1"}, {"id": "orderitemresponse_orderitemresponse", "label": "OrderItemResponse", "file_type": "code", "source_file": "C:\\Users\\bobby\\OneDrive\\Desktop\\new\\new\\src\\main\\java\\com\\example\\demo\\dto\\OrderItemResponse.java", "source_location": "L5"}, {"id": "orderitemresponse_orderitemresponse_orderitemresponse", "label": ".OrderItemResponse()", "file_type": "code", "source_file": "C:\\Users\\bobby\\OneDrive\\Desktop\\new\\new\\src\\main\\java\\com\\example\\demo\\dto\\OrderItemResponse.java", "source_location": "L15"}, {"id": "orderitemresponse_orderitemresponse_from", "label": ".from()", "file_type": "code", "source_file": "C:\\Users\\bobby\\OneDrive\\Desktop\\new\\new\\src\\main\\java\\com\\example\\demo\\dto\\OrderItemResponse.java", "source_location": "L33"}, {"id": "orderitemresponse_orderitemresponse_getordernumber", "label": ".getOrderNumber()", "file_type": "code", "source_file": "C:\\Users\\bobby\\OneDrive\\Desktop\\new\\new\\src\\main\\java\\com\\example\\demo\\dto\\OrderItemResponse.java", "source_location": "L45"}, {"id": "orderitemresponse_orderitemresponse_getsku", "label": ".getSku()", "file_type": "code", "source_file": "C:\\Users\\bobby\\OneDrive\\Desktop\\new\\new\\src\\main\\java\\com\\example\\demo\\dto\\OrderItemResponse.java", "source_location": "L49"}, {"id": "orderitemresponse_orderitemresponse_getproductid", "label": ".getProductId()", "file_type": "code", "source_file": "C:\\Users\\bobby\\OneDrive\\Desktop\\new\\new\\src\\main\\java\\com\\example\\demo\\dto\\OrderItemResponse.java", "source_location": "L53"}, {"id": "orderitemresponse_orderitemresponse_getquantity", "label": ".getQuantity()", "file_type": "code", "source_file": "C:\\Users\\bobby\\OneDrive\\Desktop\\new\\new\\src\\main\\java\\com\\example\\demo\\dto\\OrderItemResponse.java", "source_location": "L57"}, {"id": "orderitemresponse_orderitemresponse_getfulfilledquantity", "label": ".getFulfilledQuantity()", "file_type": "code", "source_file": "C:\\Users\\bobby\\OneDrive\\Desktop\\new\\new\\src\\main\\java\\com\\example\\demo\\dto\\OrderItemResponse.java", "source_location": "L61"}, {"id": "orderitemresponse_orderitemresponse_getbackorderedquantity", "label": ".getBackOrderedQuantity()", "file_type": "code", "source_file": "C:\\Users\\bobby\\OneDrive\\Desktop\\new\\new\\src\\main\\java\\com\\example\\demo\\dto\\OrderItemResponse.java", "source_location": "L65"}, {"id": "orderitemresponse_orderitemresponse_getclientid", "label": ".getClientId()", "file_type": "code", "source_file": "C:\\Users\\bobby\\OneDrive\\Desktop\\new\\new\\src\\main\\java\\com\\example\\demo\\dto\\OrderItemResponse.java", "source_location": "L69"}], "edges": [{"source": "c_users_bobby_onedrive_desktop_new_new_src_main_java_com_example_demo_dto_orderitemresponse_java", "target": "orderiteminfo", "relation": "imports", "confidence": "EXTRACTED", "source_file": "C:\\Users\\bobby\\OneDrive\\Desktop\\new\\new\\src\\main\\java\\com\\example\\demo\\dto\\OrderItemResponse.java", "source_location": "L3", "weight": 1.0}, {"source": "c_users_bobby_onedrive_desktop_new_new_src_main_java_com_example_demo_dto_orderitemresponse_java", "target": "orderitemresponse_orderitemresponse", "relation": "contains", "confidence": "EXTRACTED", "source_file": "C:\\Users\\bobby\\OneDrive\\Desktop\\new\\new\\src\\main\\java\\com\\example\\demo\\dto\\OrderItemResponse.java", "source_location": "L5", "weight": 1.0}, {"source": "orderitemresponse_orderitemresponse", "target": "orderitemresponse_orderitemresponse_orderitemresponse", "relation": "method", "confidence": "EXTRACTED", "source_file": "C:\\Users\\bobby\\OneDrive\\Desktop\\new\\new\\src\\main\\java\\com\\example\\demo\\dto\\OrderItemResponse.java", "source_location": "L15", "weight": 1.0}, {"source": "orderitemresponse_orderitemresponse", "target": "orderitemresponse_orderitemresponse_from", "relation": "method", "confidence": "EXTRACTED", "source_file": "C:\\Users\\bobby\\OneDrive\\Desktop\\new\\new\\src\\main\\java\\com\\example\\demo\\dto\\OrderItemResponse.java", "source_location": "L33", "weight": 1.0}, {"source": "orderitemresponse_orderitemresponse", "target": "orderitemresponse_orderitemresponse_getordernumber", "relation": "method", "confidence": "EXTRACTED", "source_file": "C:\\Users\\bobby\\OneDrive\\Desktop\\new\\new\\src\\main\\java\\com\\example\\demo\\dto\\OrderItemResponse.java", "source_location": "L45", "weight": 1.0}, {"source": "orderitemresponse_orderitemresponse", "target": "orderitemresponse_orderitemresponse_getsku", "relation": "method", "confidence": "EXTRACTED", "source_file": "C:\\Users\\bobby\\OneDrive\\Desktop\\new\\new\\src\\main\\java\\com\\example\\demo\\dto\\OrderItemResponse.java", "source_location": "L49", "weight": 1.0}, {"source": "orderitemresponse_orderitemresponse", "target": "orderitemresponse_orderitemresponse_getproductid", "relation": "method", "confidence": "EXTRACTED", "source_file": "C:\\Users\\bobby\\OneDrive\\Desktop\\new\\new\\src\\main\\java\\com\\example\\demo\\dto\\OrderItemResponse.java", "source_location": "L53", "weight": 1.0}, {"source": "orderitemresponse_orderitemresponse", "target": "orderitemresponse_orderitemresponse_getquantity", "relation": "method", "confidence": "EXTRACTED", "source_file": "C:\\Users\\bobby\\OneDrive\\Desktop\\new\\new\\src\\main\\java\\com\\example\\demo\\dto\\OrderItemResponse.java", "source_location": "L57", "weight": 1.0}, {"source": "orderitemresponse_orderitemresponse", "target": "orderitemresponse_orderitemresponse_getfulfilledquantity", "relation": "method", "confidence": "EXTRACTED", "source_file": "C:\\Users\\bobby\\OneDrive\\Desktop\\new\\new\\src\\main\\java\\com\\example\\demo\\dto\\OrderItemResponse.java", "source_location": "L61", "weight": 1.0}, {"source": "orderitemresponse_orderitemresponse", "target": "orderitemresponse_orderitemresponse_getbackorderedquantity", "relation": "method", "confidence": "EXTRACTED", "source_file": "C:\\Users\\bobby\\OneDrive\\Desktop\\new\\new\\src\\main\\java\\com\\example\\demo\\dto\\OrderItemResponse.java", "source_location": "L65", "weight": 1.0}, {"source": "orderitemresponse_orderitemresponse", "target": "orderitemresponse_orderitemresponse_getclientid", "relation": "method", "confidence": "EXTRACTED", "source_file": "C:\\Users\\bobby\\OneDrive\\Desktop\\new\\new\\src\\main\\java\\com\\example\\demo\\dto\\OrderItemResponse.java", "source_location": "L69", "weight": 1.0}, {"source": "orderitemresponse_orderitemresponse_from", "target": "orderitemresponse_orderitemresponse_getordernumber", "relation": "calls", "confidence": "EXTRACTED", "source_file": "C:\\Users\\bobby\\OneDrive\\Desktop\\new\\new\\src\\main\\java\\com\\example\\demo\\dto\\OrderItemResponse.java", "source_location": "L35", "weight": 1.0}, {"source": "orderitemresponse_orderitemresponse_from", "target": "orderitemresponse_orderitemresponse_getsku", "relation": "calls", "confidence": "EXTRACTED", "source_file": "C:\\Users\\bobby\\OneDrive\\Desktop\\new\\new\\src\\main\\java\\com\\example\\demo\\dto\\OrderItemResponse.java", "source_location": "L36", "weight": 1.0}, {"source": "orderitemresponse_orderitemresponse_from", "target": "orderitemresponse_orderitemresponse_getproductid", "relation": "calls", "confidence": "EXTRACTED", "source_file": "C:\\Users\\bobby\\OneDrive\\Desktop\\new\\new\\src\\main\\java\\com\\example\\demo\\dto\\OrderItemResponse.java", "source_location": "L37", "weight": 1.0}, {"source": "orderitemresponse_orderitemresponse_from", "target": "orderitemresponse_orderitemresponse_getquantity", "relation": "calls", "confidence": "EXTRACTED", "source_file": "C:\\Users\\bobby\\OneDrive\\Desktop\\new\\new\\src\\main\\java\\com\\example\\demo\\dto\\OrderItemResponse.java", "source_location": "L38", "weight": 1.0}, {"source": "orderitemresponse_orderitemresponse_from", "target": "orderitemresponse_orderitemresponse_getfulfilledquantity", "relation": "calls", "confidence": "EXTRACTED", "source_file": "C:\\Users\\bobby\\OneDrive\\Desktop\\new\\new\\src\\main\\java\\com\\example\\demo\\dto\\OrderItemResponse.java", "source_location": "L39", "weight": 1.0}, {"source": "orderitemresponse_orderitemresponse_from", "target": "orderitemresponse_orderitemresponse_getclientid", "relation": "calls", "confidence": "EXTRACTED", "source_file": "C:\\Users\\bobby\\OneDrive\\Desktop\\new\\new\\src\\main\\java\\com\\example\\demo\\dto\\OrderItemResponse.java", "source_location": "L41", "weight": 1.0}], "raw_calls": []}